event_trader/__init__.py
event_trader/base_stocks.py
event_trader/config.py
event_trader/demo_account.py
event_trader/stock_info.py
event_trader/stocks_manager.py
event_trader/strategies/__init__.py
event_trader/strategies/base_strategy.py
event_trader/strategies/boll_strategy.py
event_trader/strategies/kdj_strategy.py
event_trader/strategies/ma1_strategy.py
event_trader/strategies/ma2_strategy.py
event_trader/strategies/macd_strategy.py
event_trader/strategies/pd_strategy.py
event_trader/strategies/vma_strategy.py
event_trader/utils.py
event_trader-0.1.16.dist-info/METADATA
event_trader-0.1.16.dist-info/WHEEL
event_trader-0.1.16.dist-info/entry_points.txt
event_trader-0.1.16.dist-info/RECORD
