Metadata-Version: 2.3
Name: event-trader
Version: 0.1.16
Summary: 量化交易-选股策略-自定义参数指标
Author: sjzsdu
Author-email: 122828837@qq.com
Requires-Python: >=3.10,<3.13
Classifier: Programming Language :: Python :: 3
Classifier: Programming Language :: Python :: 3.10
Classifier: Programming Language :: Python :: 3.11
Classifier: Programming Language :: Python :: 3.12
Requires-Dist: china-stock-data (>=0.1.12,<0.2.0)
Requires-Dist: matplotlib (>=3.9.2,<4.0.0)
Requires-Dist: mplfinance (>=0.12.10b0,<0.13.0)
Requires-Dist: pandas (>=2.2.3,<3.0.0)
Requires-Dist: pymysql (>=1.1.1,<2.0.0)
Requires-Dist: python-dotenv (>=1.0.1,<2.0.0)
Requires-Dist: sqlalchemy (>=2.0.36,<3.0.0)
Requires-Dist: typer (>=0.15.1,<0.16.0)
